amo2kinto/__init__.py
amo2kinto/amo.py
amo2kinto/compare.py
amo2kinto/constants.py
amo2kinto/exporter.py
amo2kinto/generator.py
amo2kinto/kinto.py
amo2kinto/logger.py
amo2kinto/synchronize.py
amo2kinto/templates/base.tpl
amo2kinto/templates/collection.tpl
amo2kinto/templates/record.tpl
amo2kinto/tests/__init__.py
amo2kinto/tests/test_amo.py
amo2kinto/tests/test_compare.py
amo2kinto/tests/test_exporter.py
amo2kinto/tests/test_generator.py
amo2kinto/tests/test_kinto.py
amo2kinto/tests/test_synchronize.py
amo2kinto/tests/fixtures/blocklist.xml
amo2kinto/tests/fixtures/blocklists.json
amo2kinto/tests/fixtures/fennec-blocklist.xml
amo2kinto/tests/fixtures/generated-blocklist.xml
amo2kinto-4.0.2.dist-info/LICENSE
amo2kinto-4.0.2.dist-info/METADATA
amo2kinto-4.0.2.dist-info/WHEEL
amo2kinto-4.0.2.dist-info/entry_points.txt
amo2kinto-4.0.2.dist-info/top_level.txt
amo2kinto-4.0.2.dist-info/RECORD
