Metadata-Version: 2.1
Name: amo2kinto
Version: 4.0.2
Summary: Generate a blocklists.xml file from the Kinto collections.
Home-page: https://github.com/mozilla-services/amo2kinto
Author: Mozilla Services
Author-email: services-dev@mozilla.com
License: Apache License (2.0)
Keywords: web services
Platform: UNKNOWN
Classifier: Programming Language :: Python
Classifier: Programming Language :: Python :: 3
Classifier: Programming Language :: Python :: 3.5
Classifier: Programming Language :: Python :: 3.6
Classifier: License :: OSI Approved :: Apache Software License
Requires-Dist: jinja2
Requires-Dist: kinto-http (>=8)
Requires-Dist: lxml
Requires-Dist: python-dateutil
